evilfunctools/__init__.py
evilfunctools/compose.py
evilfunctools/decorators.py
evilfunctools/py.typed
evilutils/__init__.py
evilutils/__main__.py
evilutils/info.py
evilutils/py.typed
evilutils-0.1.1.dist-info/LICENSE
evilutils-0.1.1.dist-info/METADATA
evilutils-0.1.1.dist-info/WHEEL
evilutils-0.1.1.dist-info/top_level.txt
evilutils-0.1.1.dist-info/RECORD
