Metadata-Version: 2.2
Name: evilutils
Version: 0.1.1
Summary: All of the utils I don't want to write twice.
Author-email: Ernest Izdebski <44341687+ernieIzde8ski@users.noreply.github.com>
License: Copyright 2025-present Ernest Izdebski
Project-URL: Homepage, https://github.com/ernieIzde8ski/evilutils
Project-URL: Issues, https://github.com/ernieIzde8ski/evilutils/issues
Classifier: Programming Language :: Python :: 3
Classifier: License :: OSI Approved :: MIT License
Classifier: Operating System :: OS Independent
Requires-Python: >=3.12
License-File: LICENSE
Requires-Dist: typing_extensions>=4.12.2
